{"ProjectModelId":"P147_102","ProjectID":147,"ProjectName":"โครงการ Train","ModelID":102,"ModelName":"20118-400007_งานสโมสร+สระว่ายน้ำ งวดที่ 7","FModel":{"ModelID":102,"ModelCode":null,"ModelName":"20118-400007_งานสโมสร+สระว่ายน้ำ งวดที่ 7","ModelType":"F","ModelTypeName":"สาธาฯ","CreatedBy":5272,"CreatedByName":"นางสาวธีรนันท์ กรศรีทิพา","CreatedDate":"2015-09-30T18:54:49.607","ModifiedBy":5272,"ModifiedByName":"นางสาวธีรนันท์ กรศรีทิพา","ModifiedDate":"2015-09-30T18:54:49.607","DataRelatedChangeCode":"daba82fc-1cf6-438a-aac8-c019da8c7600","PartialEndProduct":false,"PartialEndProductName":"N"},"FPhases":[{"ModelID":102,"ModelCode":null,"ModelName":"20118-400007_งานสโมสร+สระว่ายน้ำ งวดที่ 7","ModelType":"F","ModelTypeName":"สาธาฯ","PhaseID":732,"PhaseName":"งานหลังคา","PhaseSeq":1,"PhaseType":"2","Progress":10.00,"UseOnStartProgress":null,"UseOnFinishProgress":null,"UseOnFinish":null,"CreatedBy":2420,"CreatedByName":"นายหฤษฎ์ เวชากุล","CreatedDate":"2015-09-30T19:45:52.22","ModifiedBy":2420,"ModifiedByName":"นายหฤษฎ์ เวชากุล","ModifiedDate":"2015-09-30T19:45:52.22","DeletedBy":null,"DeletedDate":null,"PlanProcessDay":15},{"ModelID":102,"ModelCode":null,"ModelName":"20118-400007_งานสโมสร+สระว่ายน้ำ งวดที่ 7","ModelType":"F","ModelTypeName":"สาธาฯ","PhaseID":733,"PhaseName":"งานผนัง ภายนอก","PhaseSeq":1,"PhaseType":"2","Progress":10.00,"UseOnStartProgress":null,"UseOnFinishProgress":null,"UseOnFinish":null,"CreatedBy":2420,"CreatedByName":"นายหฤษฎ์ เวชากุล","CreatedDate":"2015-09-30T19:45:52.22","ModifiedBy":2420,"ModifiedByName":"นายหฤษฎ์ เวชากุล","ModifiedDate":"2015-09-30T19:45:52.22","DeletedBy":null,"DeletedDate":null,"PlanProcessDay":15},{"ModelID":102,"ModelCode":null,"ModelName":"20118-400007_งานสโมสร+สระว่ายน้ำ งวดที่ 7","ModelType":"F","ModelTypeName":"สาธาฯ","PhaseID":734,"PhaseName":"วงกบและบานประตู ภายนอก","PhaseSeq":1,"PhaseType":"2","Progress":10.00,"UseOnStartProgress":null,"UseOnFinishProgress":null,"UseOnFinish":null,"CreatedBy":2420,"CreatedByName":"นายหฤษฎ์ เวชากุล","CreatedDate":"2015-09-30T19:45:52.22","ModifiedBy":2420,"ModifiedByName":"นายหฤษฎ์ เวชากุล","ModifiedDate":"2015-09-30T19:45:52.22","DeletedBy":null,"DeletedDate":null,"PlanProcessDay":15},{"ModelID":102,"ModelCode":null,"ModelName":"20118-400007_งานสโมสร+สระว่ายน้ำ งวดที่ 7","ModelType":"F","ModelTypeName":"สาธาฯ","PhaseID":735,"PhaseName":"วัสดุตกแต่งผิว ภายนอก","PhaseSeq":1,"PhaseType":"2","Progress":10.00,"UseOnStartProgress":null,"UseOnFinishProgress":null,"UseOnFinish":null,"CreatedBy":2420,"CreatedByName":"นายหฤษฎ์ เวชากุล","CreatedDate":"2015-09-30T19:45:52.22","ModifiedBy":2420,"ModifiedByName":"นายหฤษฎ์ เวชากุล","ModifiedDate":"2015-09-30T19:45:52.22","DeletedBy":null,"DeletedDate":null,"PlanProcessDay":15},{"ModelID":102,"ModelCode":null,"ModelName":"20118-400007_งานสโมสร+สระว่ายน้ำ งวดที่ 7","ModelType":"F","ModelTypeName":"สาธาฯ","PhaseID":736,"PhaseName":"ฝ้าชายคาภายนอก","PhaseSeq":1,"PhaseType":"2","Progress":10.00,"UseOnStartProgress":null,"UseOnFinishProgress":null,"UseOnFinish":null,"CreatedBy":2420,"CreatedByName":"นายหฤษฎ์ เวชากุล","CreatedDate":"2015-09-30T19:45:52.22","ModifiedBy":2420,"ModifiedByName":"นายหฤษฎ์ เวชากุล","ModifiedDate":"2015-09-30T19:45:52.22","DeletedBy":null,"DeletedDate":null,"PlanProcessDay":15},{"ModelID":102,"ModelCode":null,"ModelName":"20118-400007_งานสโมสร+สระว่ายน้ำ งวดที่ 7","ModelType":"F","ModelTypeName":"สาธาฯ","PhaseID":737,"PhaseName":"งานระบบไฟฟ้า,ประปา ภายนอก","PhaseSeq":1,"PhaseType":"2","Progress":10.00,"UseOnStartProgress":null,"UseOnFinishProgress":null,"UseOnFinish":null,"CreatedBy":2420,"CreatedByName":"นายหฤษฎ์ เวชากุล","CreatedDate":"2015-09-30T19:45:52.22","ModifiedBy":2420,"ModifiedByName":"นายหฤษฎ์ เวชากุล","ModifiedDate":"2015-09-30T19:45:52.22","DeletedBy":null,"DeletedDate":null,"PlanProcessDay":15},{"ModelID":102,"ModelCode":null,"ModelName":"20118-400007_งานสโมสร+สระว่ายน้ำ งวดที่ 7","ModelType":"F","ModelTypeName":"สาธาฯ","PhaseID":738,"PhaseName":"งานพื้น ภายใน","PhaseSeq":1,"PhaseType":"2","Progress":10.00,"UseOnStartProgress":null,"UseOnFinishProgress":null,"UseOnFinish":null,"CreatedBy":2420,"CreatedByName":"นายหฤษฎ์ เวชากุล","CreatedDate":"2015-09-30T19:45:52.22","ModifiedBy":2420,"ModifiedByName":"นายหฤษฎ์ เวชากุล","ModifiedDate":"2015-09-30T19:45:52.22","DeletedBy":null,"DeletedDate":null,"PlanProcessDay":15},{"ModelID":102,"ModelCode":null,"ModelName":"20118-400007_งานสโมสร+สระว่ายน้ำ งวดที่ 7","ModelType":"F","ModelTypeName":"สาธาฯ","PhaseID":739,"PhaseName":"งานผนัง WallPaper","PhaseSeq":1,"PhaseType":"2","Progress":10.00,"UseOnStartProgress":null,"UseOnFinishProgress":null,"UseOnFinish":null,"CreatedBy":2420,"CreatedByName":"นายหฤษฎ์ เวชากุล","CreatedDate":"2015-09-30T19:45:52.22","ModifiedBy":2420,"ModifiedByName":"นายหฤษฎ์ เวชากุล","ModifiedDate":"2015-09-30T19:45:52.22","DeletedBy":null,"DeletedDate":null,"PlanProcessDay":15},{"ModelID":102,"ModelCode":null,"ModelName":"20118-400007_งานสโมสร+สระว่ายน้ำ งวดที่ 7","ModelType":"F","ModelTypeName":"สาธาฯ","PhaseID":740,"PhaseName":"งานฝ้าภายใน","PhaseSeq":1,"PhaseType":"2","Progress":10.00,"UseOnStartProgress":null,"UseOnFinishProgress":null,"UseOnFinish":null,"CreatedBy":2420,"CreatedByName":"นายหฤษฎ์ เวชากุล","CreatedDate":"2015-09-30T19:45:52.22","ModifiedBy":2420,"ModifiedByName":"นายหฤษฎ์ เวชากุล","ModifiedDate":"2015-09-30T19:45:52.22","DeletedBy":null,"DeletedDate":null,"PlanProcessDay":15},{"ModelID":102,"ModelCode":null,"ModelName":"20118-400007_งานสโมสร+สระว่ายน้ำ งวดที่ 7","ModelType":"F","ModelTypeName":"สาธาฯ","PhaseID":741,"PhaseName":"เครื่องสำรองไฟฉุกเฉิน","PhaseSeq":1,"PhaseType":"2","Progress":10.00,"UseOnStartProgress":null,"UseOnFinishProgress":null,"UseOnFinish":null,"CreatedBy":2420,"CreatedByName":"นายหฤษฎ์ เวชากุล","CreatedDate":"2015-09-30T19:45:52.22","ModifiedBy":2420,"ModifiedByName":"นายหฤษฎ์ เวชากุล","ModifiedDate":"2015-09-30T19:45:52.22","DeletedBy":null,"DeletedDate":null,"PlanProcessDay":15},{"ModelID":102,"ModelCode":null,"ModelName":"20118-400007_งานสโมสร+สระว่ายน้ำ งวดที่ 7","ModelType":"F","ModelTypeName":"สาธาฯ","PhaseID":742,"PhaseName":"ห้องน้ำ","PhaseSeq":1,"PhaseType":"2","Progress":10.00,"UseOnStartProgress":null,"UseOnFinishProgress":null,"UseOnFinish":null,"CreatedBy":2420,"CreatedByName":"นายหฤษฎ์ เวชากุล","CreatedDate":"2015-09-30T19:45:52.22","ModifiedBy":2420,"ModifiedByName":"นายหฤษฎ์ เวชากุล","ModifiedDate":"2015-09-30T19:45:52.22","DeletedBy":null,"DeletedDate":null,"PlanProcessDay":15},{"ModelID":102,"ModelCode":null,"ModelName":"20118-400007_งานสโมสร+สระว่ายน้ำ งวดที่ 7","ModelType":"F","ModelTypeName":"สาธาฯ","PhaseID":743,"PhaseName":"ตู้ Main Breaker","PhaseSeq":1,"PhaseType":"2","Progress":10.00,"UseOnStartProgress":null,"UseOnFinishProgress":null,"UseOnFinish":null,"CreatedBy":2420,"CreatedByName":"นายหฤษฎ์ เวชากุล","CreatedDate":"2015-09-30T19:45:52.22","ModifiedBy":2420,"ModifiedByName":"นายหฤษฎ์ เวชากุล","ModifiedDate":"2015-09-30T19:45:52.22","DeletedBy":null,"DeletedDate":null,"PlanProcessDay":15},{"ModelID":102,"ModelCode":null,"ModelName":"20118-400007_งานสโมสร+สระว่ายน้ำ งวดที่ 7","ModelType":"F","ModelTypeName":"สาธาฯ","PhaseID":744,"PhaseName":"งานสระว่ายน้ำ","PhaseSeq":1,"PhaseType":"2","Progress":10.00,"UseOnStartProgress":null,"UseOnFinishProgress":null,"UseOnFinish":null,"CreatedBy":2420,"CreatedByName":"นายหฤษฎ์ เวชากุล","CreatedDate":"2015-09-30T19:45:52.22","ModifiedBy":2420,"ModifiedByName":"นายหฤษฎ์ เวชากุล","ModifiedDate":"2015-09-30T19:45:52.22","DeletedBy":null,"DeletedDate":null,"PlanProcessDay":15},{"ModelID":102,"ModelCode":null,"ModelName":"20118-400007_งานสโมสร+สระว่ายน้ำ งวดที่ 7","ModelType":"F","ModelTypeName":"สาธาฯ","PhaseID":745,"PhaseName":"งานระบบ สระว่ายน้ำ","PhaseSeq":1,"PhaseType":"2","Progress":10.00,"UseOnStartProgress":null,"UseOnFinishProgress":null,"UseOnFinish":null,"CreatedBy":2420,"CreatedByName":"นายหฤษฎ์ เวชากุล","CreatedDate":"2015-09-30T19:45:52.22","ModifiedBy":2420,"ModifiedByName":"นายหฤษฎ์ เวชากุล","ModifiedDate":"2015-09-30T19:45:52.22","DeletedBy":null,"DeletedDate":null,"PlanProcessDay":15}],"FHeaders":[{"ModelID":102,"ModelCode":null,"ModelName":"20118-400007_งานสโมสร+สระว่ายน้ำ งวดที่ 7","ModelType":"F","ModelTypeName":"สาธาฯ","PhaseID":732,"PhaseName":"งานหลังคา","PhaseSeq":1,"PhaseType":"2","Progress":10.00,"HeaderID":8578,"HeaderVersionNumber":1,"HeaderName":"รายละเอียดงาน","HeaderType":"REQ","HeaderSeq":1,"ForSe":true,"ForQA":true,"ForQAName":"Y","HeaderRemark":null,"AreaID":0,"AreaName":"","CreatedBy":2420,"CreatedByName":"นายหฤษฎ์ เวชากุล","CreatedDate":"2015-09-30T19:45:52.22","ModifiedBy":2420,"ModifiedByName":"นายหฤษฎ์ เวชากุล","ModifiedDate":"2015-09-30T19:45:52.22","GroupID":0,"GroupName":null,"DeletedBy":null,"DeletedDate":null,"IsMandatoryCapture":"Y"},{"ModelID":102,"ModelCode":null,"ModelName":"20118-400007_งานสโมสร+สระว่ายน้ำ งวดที่ 7","ModelType":"F","ModelTypeName":"สาธาฯ","PhaseID":733,"PhaseName":"งานผนัง ภายนอก","PhaseSeq":1,"PhaseType":"2","Progress":10.00,"HeaderID":8579,"HeaderVersionNumber":1,"HeaderName":"รายละเอียดงาน","HeaderType":"REQ","HeaderSeq":1,"ForSe":true,"ForQA":true,"ForQAName":"Y","HeaderRemark":null,"AreaID":0,"AreaName":"","CreatedBy":2420,"CreatedByName":"นายหฤษฎ์ เวชากุล","CreatedDate":"2015-09-30T19:45:52.22","ModifiedBy":2420,"ModifiedByName":"นายหฤษฎ์ เวชากุล","ModifiedDate":"2015-09-30T19:45:52.22","GroupID":0,"GroupName":null,"DeletedBy":null,"DeletedDate":null,"IsMandatoryCapture":"Y"},{"ModelID":102,"ModelCode":null,"ModelName":"20118-400007_งานสโมสร+สระว่ายน้ำ งวดที่ 7","ModelType":"F","ModelTypeName":"สาธาฯ","PhaseID":734,"PhaseName":"วงกบและบานประตู ภายนอก","PhaseSeq":1,"PhaseType":"2","Progress":10.00,"HeaderID":8580,"HeaderVersionNumber":1,"HeaderName":"รายละเอียดงาน","HeaderType":"REQ","HeaderSeq":1,"ForSe":true,"ForQA":true,"ForQAName":"Y","HeaderRemark":null,"AreaID":0,"AreaName":"","CreatedBy":2420,"CreatedByName":"นายหฤษฎ์ เวชากุล","CreatedDate":"2015-09-30T19:45:52.22","ModifiedBy":2420,"ModifiedByName":"นายหฤษฎ์ เวชากุล","ModifiedDate":"2015-09-30T19:45:52.22","GroupID":0,"GroupName":null,"DeletedBy":null,"DeletedDate":null,"IsMandatoryCapture":"Y"},{"ModelID":102,"ModelCode":null,"ModelName":"20118-400007_งานสโมสร+สระว่ายน้ำ งวดที่ 7","ModelType":"F","ModelTypeName":"สาธาฯ","PhaseID":735,"PhaseName":"วัสดุตกแต่งผิว ภายนอก","PhaseSeq":1,"PhaseType":"2","Progress":10.00,"HeaderID":8581,"HeaderVersionNumber":1,"HeaderName":"รายละเอียดงาน","HeaderType":"REQ","HeaderSeq":1,"ForSe":true,"ForQA":true,"ForQAName":"Y","HeaderRemark":null,"AreaID":0,"AreaName":"","CreatedBy":2420,"CreatedByName":"นายหฤษฎ์ เวชากุล","CreatedDate":"2015-09-30T19:45:52.22","ModifiedBy":2420,"ModifiedByName":"นายหฤษฎ์ เวชากุล","ModifiedDate":"2015-09-30T19:45:52.22","GroupID":0,"GroupName":null,"DeletedBy":null,"DeletedDate":null,"IsMandatoryCapture":"Y"},{"ModelID":102,"ModelCode":null,"ModelName":"20118-400007_งานสโมสร+สระว่ายน้ำ งวดที่ 7","ModelType":"F","ModelTypeName":"สาธาฯ","PhaseID":736,"PhaseName":"ฝ้าชายคาภายนอก","PhaseSeq":1,"PhaseType":"2","Progress":10.00,"HeaderID":8582,"HeaderVersionNumber":1,"HeaderName":"รายละเอียดงาน","HeaderType":"REQ","HeaderSeq":1,"ForSe":true,"ForQA":true,"ForQAName":"Y","HeaderRemark":null,"AreaID":0,"AreaName":"","CreatedBy":2420,"CreatedByName":"นายหฤษฎ์ เวชากุล","CreatedDate":"2015-09-30T19:45:52.22","ModifiedBy":2420,"ModifiedByName":"นายหฤษฎ์ เวชากุล","ModifiedDate":"2015-09-30T19:45:52.22","GroupID":0,"GroupName":null,"DeletedBy":null,"DeletedDate":null,"IsMandatoryCapture":"Y"},{"ModelID":102,"ModelCode":null,"ModelName":"20118-400007_งานสโมสร+สระว่ายน้ำ งวดที่ 7","ModelType":"F","ModelTypeName":"สาธาฯ","PhaseID":737,"PhaseName":"งานระบบไฟฟ้า,ประปา ภายนอก","PhaseSeq":1,"PhaseType":"2","Progress":10.00,"HeaderID":8583,"HeaderVersionNumber":1,"HeaderName":"รายละเอียดงาน","HeaderType":"REQ","HeaderSeq":1,"ForSe":true,"ForQA":true,"ForQAName":"Y","HeaderRemark":null,"AreaID":0,"AreaName":"","CreatedBy":2420,"CreatedByName":"นายหฤษฎ์ เวชากุล","CreatedDate":"2015-09-30T19:45:52.22","ModifiedBy":2420,"ModifiedByName":"นายหฤษฎ์ เวชากุล","ModifiedDate":"2015-09-30T19:45:52.22","GroupID":0,"GroupName":null,"DeletedBy":null,"DeletedDate":null,"IsMandatoryCapture":"Y"},{"ModelID":102,"ModelCode":null,"ModelName":"20118-400007_งานสโมสร+สระว่ายน้ำ งวดที่ 7","ModelType":"F","ModelTypeName":"สาธาฯ","PhaseID":738,"PhaseName":"งานพื้น ภายใน","PhaseSeq":1,"PhaseType":"2","Progress":10.00,"HeaderID":8584,"HeaderVersionNumber":1,"HeaderName":"รายละเอียดงาน","HeaderType":"REQ","HeaderSeq":1,"ForSe":true,"ForQA":true,"ForQAName":"Y","HeaderRemark":null,"AreaID":0,"AreaName":"","CreatedBy":2420,"CreatedByName":"นายหฤษฎ์ เวชากุล","CreatedDate":"2015-09-30T19:45:52.22","ModifiedBy":2420,"ModifiedByName":"นายหฤษฎ์ เวชากุล","ModifiedDate":"2015-09-30T19:45:52.22","GroupID":0,"GroupName":null,"DeletedBy":null,"DeletedDate":null,"IsMandatoryCapture":"Y"},{"ModelID":102,"ModelCode":null,"ModelName":"20118-400007_งานสโมสร+สระว่ายน้ำ งวดที่ 7","ModelType":"F","ModelTypeName":"สาธาฯ","PhaseID":739,"PhaseName":"งานผนัง WallPaper","PhaseSeq":1,"PhaseType":"2","Progress":10.00,"HeaderID":8585,"HeaderVersionNumber":1,"HeaderName":"รายละเอียดงาน","HeaderType":"REQ","HeaderSeq":1,"ForSe":true,"ForQA":true,"ForQAName":"Y","HeaderRemark":null,"AreaID":0,"AreaName":"","CreatedBy":2420,"CreatedByName":"นายหฤษฎ์ เวชากุล","CreatedDate":"2015-09-30T19:45:52.22","ModifiedBy":2420,"ModifiedByName":"นายหฤษฎ์ เวชากุล","ModifiedDate":"2015-09-30T19:45:52.22","GroupID":0,"GroupName":null,"DeletedBy":null,"DeletedDate":null,"IsMandatoryCapture":"Y"},{"ModelID":102,"ModelCode":null,"ModelName":"20118-400007_งานสโมสร+สระว่ายน้ำ งวดที่ 7","ModelType":"F","ModelTypeName":"สาธาฯ","PhaseID":740,"PhaseName":"งานฝ้าภายใน","PhaseSeq":1,"PhaseType":"2","Progress":10.00,"HeaderID":8586,"HeaderVersionNumber":1,"HeaderName":"รายละเอียดงาน","HeaderType":"REQ","HeaderSeq":1,"ForSe":true,"ForQA":true,"ForQAName":"Y","HeaderRemark":null,"AreaID":0,"AreaName":"","CreatedBy":2420,"CreatedByName":"นายหฤษฎ์ เวชากุล","CreatedDate":"2015-09-30T19:45:52.22","ModifiedBy":2420,"ModifiedByName":"นายหฤษฎ์ เวชากุล","ModifiedDate":"2015-09-30T19:45:52.22","GroupID":0,"GroupName":null,"DeletedBy":null,"DeletedDate":null,"IsMandatoryCapture":"Y"},{"ModelID":102,"ModelCode":null,"ModelName":"20118-400007_งานสโมสร+สระว่ายน้ำ งวดที่ 7","ModelType":"F","ModelTypeName":"สาธาฯ","PhaseID":741,"PhaseName":"เครื่องสำรองไฟฉุกเฉิน","PhaseSeq":1,"PhaseType":"2","Progress":10.00,"HeaderID":8587,"HeaderVersionNumber":1,"HeaderName":"รายละเอียดงาน","HeaderType":"REQ","HeaderSeq":1,"ForSe":true,"ForQA":true,"ForQAName":"Y","HeaderRemark":null,"AreaID":0,"AreaName":"","CreatedBy":2420,"CreatedByName":"นายหฤษฎ์ เวชากุล","CreatedDate":"2015-09-30T19:45:52.22","ModifiedBy":2420,"ModifiedByName":"นายหฤษฎ์ เวชากุล","ModifiedDate":"2015-09-30T19:45:52.22","GroupID":0,"GroupName":null,"DeletedBy":null,"DeletedDate":null,"IsMandatoryCapture":"Y"},{"ModelID":102,"ModelCode":null,"ModelName":"20118-400007_งานสโมสร+สระว่ายน้ำ งวดที่ 7","ModelType":"F","ModelTypeName":"สาธาฯ","PhaseID":742,"PhaseName":"ห้องน้ำ","PhaseSeq":1,"PhaseType":"2","Progress":10.00,"HeaderID":8588,"HeaderVersionNumber":1,"HeaderName":"รายละเอียดงาน","HeaderType":"REQ","HeaderSeq":1,"ForSe":true,"ForQA":true,"ForQAName":"Y","HeaderRemark":null,"AreaID":0,"AreaName":"","CreatedBy":2420,"CreatedByName":"นายหฤษฎ์ เวชากุล","CreatedDate":"2015-09-30T19:45:52.22","ModifiedBy":2420,"ModifiedByName":"นายหฤษฎ์ เวชากุล","ModifiedDate":"2015-09-30T19:45:52.22","GroupID":0,"GroupName":null,"DeletedBy":null,"DeletedDate":null,"IsMandatoryCapture":"Y"},{"ModelID":102,"ModelCode":null,"ModelName":"20118-400007_งานสโมสร+สระว่ายน้ำ งวดที่ 7","ModelType":"F","ModelTypeName":"สาธาฯ","PhaseID":743,"PhaseName":"ตู้ Main Breaker","PhaseSeq":1,"PhaseType":"2","Progress":10.00,"HeaderID":8589,"HeaderVersionNumber":1,"HeaderName":"รายละเอียดงาน","HeaderType":"REQ","HeaderSeq":1,"ForSe":true,"ForQA":true,"ForQAName":"Y","HeaderRemark":null,"AreaID":0,"AreaName":"","CreatedBy":2420,"CreatedByName":"นายหฤษฎ์ เวชากุล","CreatedDate":"2015-09-30T19:45:52.22","ModifiedBy":2420,"ModifiedByName":"นายหฤษฎ์ เวชากุล","ModifiedDate":"2015-09-30T19:45:52.22","GroupID":0,"GroupName":null,"DeletedBy":null,"DeletedDate":null,"IsMandatoryCapture":"Y"},{"ModelID":102,"ModelCode":null,"ModelName":"20118-400007_งานสโมสร+สระว่ายน้ำ งวดที่ 7","ModelType":"F","ModelTypeName":"สาธาฯ","PhaseID":744,"PhaseName":"งานสระว่ายน้ำ","PhaseSeq":1,"PhaseType":"2","Progress":10.00,"HeaderID":8590,"HeaderVersionNumber":1,"HeaderName":"รายละเอียดงาน","HeaderType":"REQ","HeaderSeq":1,"ForSe":true,"ForQA":true,"ForQAName":"Y","HeaderRemark":null,"AreaID":0,"AreaName":"","CreatedBy":2420,"CreatedByName":"นายหฤษฎ์ เวชากุล","CreatedDate":"2015-09-30T19:45:52.22","ModifiedBy":2420,"ModifiedByName":"นายหฤษฎ์ เวชากุล","ModifiedDate":"2015-09-30T19:45:52.22","GroupID":0,"GroupName":null,"DeletedBy":null,"DeletedDate":null,"IsMandatoryCapture":"Y"},{"ModelID":102,"ModelCode":null,"ModelName":"20118-400007_งานสโมสร+สระว่ายน้ำ งวดที่ 7","ModelType":"F","ModelTypeName":"สาธาฯ","PhaseID":745,"PhaseName":"งานระบบ สระว่ายน้ำ","PhaseSeq":1,"PhaseType":"2","Progress":10.00,"HeaderID":8591,"HeaderVersionNumber":1,"HeaderName":"รายละเอียดงาน","HeaderType":"REQ","HeaderSeq":1,"ForSe":true,"ForQA":true,"ForQAName":"Y","HeaderRemark":null,"AreaID":0,"AreaName":"","CreatedBy":2420,"CreatedByName":"นายหฤษฎ์ เวชากุล","CreatedDate":"2015-09-30T19:45:52.22","ModifiedBy":2420,"ModifiedByName":"นายหฤษฎ์ เวชากุล","ModifiedDate":"2015-09-30T19:45:52.22","GroupID":0,"GroupName":null,"DeletedBy":null,"DeletedDate":null,"IsMandatoryCapture":"Y"}],"FDetails":[{"DetailID":35202,"VersionNumber":1,"HeaderID":8578,"ScoreID":0,"SubjectID":null,"GroupName":"","DetailName":"กระเบื้องไม่ร้าว,บิ่น","Seq":1,"Status":null,"Remark":null,"CreatedBy":2420,"CreatedDate":"2015-09-30T19:45:52.22","ModifiedBy":2420,"ModifiedDate":"2015-09-30T19:45:52.22","DeletedBy":null,"DeletedDate":null,"RefID":null,"HelpMStorageServerId":null,"HelpMFilePath":null,"HelpMMineType":null,"HelpMFileLength":null,"HelpMCreateDate":null,"HelpMUpdateDate":null,"DetailType":"Major","ForSE":true,"ForQA":true,"IsMandatoryCapture":"Y"},{"DetailID":35203,"VersionNumber":1,"HeaderID":8578,"ScoreID":0,"SubjectID":null,"GroupName":"","DetailName":"กระเบื้องสะอาดไม่มีสีเลอะ","Seq":2,"Status":null,"Remark":null,"CreatedBy":2420,"CreatedDate":"2015-09-30T19:45:52.22","ModifiedBy":2420,"ModifiedDate":"2015-09-30T19:45:52.22","DeletedBy":null,"DeletedDate":null,"RefID":null,"HelpMStorageServerId":null,"HelpMFilePath":null,"HelpMMineType":null,"HelpMFileLength":null,"HelpMCreateDate":null,"HelpMUpdateDate":null,"DetailType":"Major","ForSE":true,"ForQA":true,"IsMandatoryCapture":"Y"},{"DetailID":35204,"VersionNumber":1,"HeaderID":8579,"ScoreID":0,"SubjectID":null,"GroupName":"","DetailName":"ผนังไม่มีรอยแตก,ร้าว(งานผนัง)","Seq":1,"Status":null,"Remark":null,"CreatedBy":2420,"CreatedDate":"2015-09-30T19:45:52.22","ModifiedBy":2420,"ModifiedDate":"2015-09-30T19:45:52.22","DeletedBy":null,"DeletedDate":null,"RefID":null,"HelpMStorageServerId":null,"HelpMFilePath":null,"HelpMMineType":null,"HelpMFileLength":null,"HelpMCreateDate":null,"HelpMUpdateDate":null,"DetailType":"Major","ForSE":true,"ForQA":true,"IsMandatoryCapture":"Y"},{"DetailID":35205,"VersionNumber":1,"HeaderID":8579,"ScoreID":0,"SubjectID":null,"GroupName":"","DetailName":"สีผนังไม่ด่าง,เรียบสม่ำเสมอ(งานผนัง)","Seq":2,"Status":null,"Remark":null,"CreatedBy":2420,"CreatedDate":"2015-09-30T19:45:52.22","ModifiedBy":2420,"ModifiedDate":"2015-09-30T19:45:52.22","DeletedBy":null,"DeletedDate":null,"RefID":null,"HelpMStorageServerId":null,"HelpMFilePath":null,"HelpMMineType":null,"HelpMFileLength":null,"HelpMCreateDate":null,"HelpMUpdateDate":null,"DetailType":"Major","ForSE":true,"ForQA":true,"IsMandatoryCapture":"Y"},{"DetailID":35206,"VersionNumber":1,"HeaderID":8580,"ScoreID":0,"SubjectID":null,"GroupName":"","DetailName":"เปิดปิดสะดวก,อุปกรณ์ครบ(วงกบและบานประตู)","Seq":1,"Status":null,"Remark":null,"CreatedBy":2420,"CreatedDate":"2015-09-30T19:45:52.22","ModifiedBy":2420,"ModifiedDate":"2015-09-30T19:45:52.22","DeletedBy":null,"DeletedDate":null,"RefID":null,"HelpMStorageServerId":null,"HelpMFilePath":null,"HelpMMineType":null,"HelpMFileLength":null,"HelpMCreateDate":null,"HelpMUpdateDate":null,"DetailType":"Major","ForSE":true,"ForQA":true,"IsMandatoryCapture":"Y"},{"DetailID":35207,"VersionNumber":1,"HeaderID":8580,"ScoreID":0,"SubjectID":null,"GroupName":"","DetailName":"วงกบบานกรอบไม่บุบ,ไม่ถลอก(วงกบและบานประตู)","Seq":2,"Status":null,"Remark":null,"CreatedBy":2420,"CreatedDate":"2015-09-30T19:45:52.22","ModifiedBy":2420,"ModifiedDate":"2015-09-30T19:45:52.22","DeletedBy":null,"DeletedDate":null,"RefID":null,"HelpMStorageServerId":null,"HelpMFilePath":null,"HelpMMineType":null,"HelpMFileLength":null,"HelpMCreateDate":null,"HelpMUpdateDate":null,"DetailType":"Major","ForSE":true,"ForQA":true,"IsMandatoryCapture":"Y"},{"DetailID":35208,"VersionNumber":1,"HeaderID":8580,"ScoreID":0,"SubjectID":null,"GroupName":"","DetailName":"วงกบบานสะอาดสีไม่เลอะ(วงกบและบานประตู)","Seq":3,"Status":null,"Remark":null,"CreatedBy":2420,"CreatedDate":"2015-09-30T19:45:52.22","ModifiedBy":2420,"ModifiedDate":"2015-09-30T19:45:52.22","DeletedBy":null,"DeletedDate":null,"RefID":null,"HelpMStorageServerId":null,"HelpMFilePath":null,"HelpMMineType":null,"HelpMFileLength":null,"HelpMCreateDate":null,"HelpMUpdateDate":null,"DetailType":"Major","ForSE":true,"ForQA":true,"IsMandatoryCapture":"Y"},{"DetailID":35209,"VersionNumber":1,"HeaderID":8581,"ScoreID":0,"SubjectID":null,"GroupName":"","DetailName":"กระเบื้อง,ทรายล้าง,หินเทียมแปะผนังไม่มีรอยร้าว,บิ่น(วัสดุตกแต่งผิว)","Seq":1,"Status":null,"Remark":null,"CreatedBy":2420,"CreatedDate":"2015-09-30T19:45:52.22","ModifiedBy":2420,"ModifiedDate":"2015-09-30T19:45:52.22","DeletedBy":null,"DeletedDate":null,"RefID":null,"HelpMStorageServerId":null,"HelpMFilePath":null,"HelpMMineType":null,"HelpMFileLength":null,"HelpMCreateDate":null,"HelpMUpdateDate":null,"DetailType":"Major","ForSE":true,"ForQA":true,"IsMandatoryCapture":"Y"},{"DetailID":35210,"VersionNumber":1,"HeaderID":8581,"ScoreID":0,"SubjectID":null,"GroupName":"","DetailName":"สีไม่ด่าง,เรียบสม่ำเสมอ(วัสดุตกแต่งผิว)","Seq":2,"Status":null,"Remark":null,"CreatedBy":2420,"CreatedDate":"2015-09-30T19:45:52.22","ModifiedBy":2420,"ModifiedDate":"2015-09-30T19:45:52.22","DeletedBy":null,"DeletedDate":null,"RefID":null,"HelpMStorageServerId":null,"HelpMFilePath":null,"HelpMMineType":null,"HelpMFileLength":null,"HelpMCreateDate":null,"HelpMUpdateDate":null,"DetailType":"Major","ForSE":true,"ForQA":true,"IsMandatoryCapture":"Y"},{"DetailID":35211,"VersionNumber":1,"HeaderID":8582,"ScoreID":0,"SubjectID":null,"GroupName":"","DetailName":"ฝ้าวัสดุไม่แตก,ร้าว,บิ่น(ฝ้าชายคาภายนอก)","Seq":1,"Status":null,"Remark":null,"CreatedBy":2420,"CreatedDate":"2015-09-30T19:45:52.22","ModifiedBy":2420,"ModifiedDate":"2015-09-30T19:45:52.22","DeletedBy":null,"DeletedDate":null,"RefID":null,"HelpMStorageServerId":null,"HelpMFilePath":null,"HelpMMineType":null,"HelpMFileLength":null,"HelpMCreateDate":null,"HelpMUpdateDate":null,"DetailType":"Major","ForSE":true,"ForQA":true,"IsMandatoryCapture":"Y"},{"DetailID":35212,"VersionNumber":1,"HeaderID":8582,"ScoreID":0,"SubjectID":null,"GroupName":"","DetailName":"ฝ้าผิวเรียบไม่เห็นรอยต่อ(ฝ้าชายคาภายนอก)","Seq":2,"Status":null,"Remark":null,"CreatedBy":2420,"CreatedDate":"2015-09-30T19:45:52.22","ModifiedBy":2420,"ModifiedDate":"2015-09-30T19:45:52.22","DeletedBy":null,"DeletedDate":null,"RefID":null,"HelpMStorageServerId":null,"HelpMFilePath":null,"HelpMMineType":null,"HelpMFileLength":null,"HelpMCreateDate":null,"HelpMUpdateDate":null,"DetailType":"Major","ForSE":true,"ForQA":true,"IsMandatoryCapture":"Y"},{"DetailID":35213,"VersionNumber":1,"HeaderID":8582,"ScoreID":0,"SubjectID":null,"GroupName":"","DetailName":"สีฝ้าชายคาไม่ด่าง,เรียบสม่ำเสมอ(ฝ้าชายคาภายนอก)","Seq":3,"Status":null,"Remark":null,"CreatedBy":2420,"CreatedDate":"2015-09-30T19:45:52.22","ModifiedBy":2420,"ModifiedDate":"2015-09-30T19:45:52.22","DeletedBy":null,"DeletedDate":null,"RefID":null,"HelpMStorageServerId":null,"HelpMFilePath":null,"HelpMMineType":null,"HelpMFileLength":null,"HelpMCreateDate":null,"HelpMUpdateDate":null,"DetailType":"Major","ForSE":true,"ForQA":true,"IsMandatoryCapture":"Y"},{"DetailID":35214,"VersionNumber":1,"HeaderID":8583,"ScoreID":0,"SubjectID":null,"GroupName":"","DetailName":"หลอดไฟติดครบทุกหลอด(งานระบบไฟฟ้า,ประปา)","Seq":1,"Status":null,"Remark":null,"CreatedBy":2420,"CreatedDate":"2015-09-30T19:45:52.22","ModifiedBy":2420,"ModifiedDate":"2015-09-30T19:45:52.22","DeletedBy":null,"DeletedDate":null,"RefID":null,"HelpMStorageServerId":null,"HelpMFilePath":null,"HelpMMineType":null,"HelpMFileLength":null,"HelpMCreateDate":null,"HelpMUpdateDate":null,"DetailType":"Major","ForSE":true,"ForQA":true,"IsMandatoryCapture":"Y"},{"DetailID":35215,"VersionNumber":1,"HeaderID":8583,"ScoreID":0,"SubjectID":null,"GroupName":"","DetailName":"ระบบน้ำใช้งานได้,ท่อไม่ตัน,ไม่มีกลิ่น(งานระบบไฟฟ้า,ประปา)","Seq":2,"Status":null,"Remark":null,"CreatedBy":2420,"CreatedDate":"2015-09-30T19:45:52.22","ModifiedBy":2420,"ModifiedDate":"2015-09-30T19:45:52.22","DeletedBy":null,"DeletedDate":null,"RefID":null,"HelpMStorageServerId":null,"HelpMFilePath":null,"HelpMMineType":null,"HelpMFileLength":null,"HelpMCreateDate":null,"HelpMUpdateDate":null,"DetailType":"Major","ForSE":true,"ForQA":true,"IsMandatoryCapture":"Y"},{"DetailID":35216,"VersionNumber":1,"HeaderID":8584,"ScoreID":0,"SubjectID":null,"GroupName":"","DetailName":"พื้นไม่กระเดิด,พิ้นไม่หลุดร่อน,ไม่บิ่นมไม่ร้าว(งานพิ้น)","Seq":1,"Status":null,"Remark":null,"CreatedBy":2420,"CreatedDate":"2015-09-30T19:45:52.22","ModifiedBy":2420,"ModifiedDate":"2015-09-30T19:45:52.22","DeletedBy":null,"DeletedDate":null,"RefID":null,"HelpMStorageServerId":null,"HelpMFilePath":null,"HelpMMineType":null,"HelpMFileLength":null,"HelpMCreateDate":null,"HelpMUpdateDate":null,"DetailType":"Major","ForSE":true,"ForQA":true,"IsMandatoryCapture":"Y"},{"DetailID":35217,"VersionNumber":1,"HeaderID":8584,"ScoreID":0,"SubjectID":null,"GroupName":"","DetailName":"สีไม่เพี้ยน(งานพิ้น)","Seq":2,"Status":null,"Remark":null,"CreatedBy":2420,"CreatedDate":"2015-09-30T19:45:52.22","ModifiedBy":2420,"ModifiedDate":"2015-09-30T19:45:52.22","DeletedBy":null,"DeletedDate":null,"RefID":null,"HelpMStorageServerId":null,"HelpMFilePath":null,"HelpMMineType":null,"HelpMFileLength":null,"HelpMCreateDate":null,"HelpMUpdateDate":null,"DetailType":"Major","ForSE":true,"ForQA":true,"IsMandatoryCapture":"Y"},{"DetailID":35218,"VersionNumber":1,"HeaderID":8585,"ScoreID":0,"SubjectID":null,"GroupName":"","DetailName":"Wall ไม่มีรอยฉีกขาด,ตัด,ปะ(งานผนัง WallPaper)","Seq":1,"Status":null,"Remark":null,"CreatedBy":2420,"CreatedDate":"2015-09-30T19:45:52.22","ModifiedBy":2420,"ModifiedDate":"2015-09-30T19:45:52.22","DeletedBy":null,"DeletedDate":null,"RefID":null,"HelpMStorageServerId":null,"HelpMFilePath":null,"HelpMMineType":null,"HelpMFileLength":null,"HelpMCreateDate":null,"HelpMUpdateDate":null,"DetailType":"Major","ForSE":true,"ForQA":true,"IsMandatoryCapture":"Y"},{"DetailID":35219,"VersionNumber":1,"HeaderID":8585,"ScoreID":0,"SubjectID":null,"GroupName":"","DetailName":"มุมผนัง,เสาใต้ Wallไม่มีโพรงอากาศ(งานผนัง WallPaper)","Seq":2,"Status":null,"Remark":null,"CreatedBy":2420,"CreatedDate":"2015-09-30T19:45:52.22","ModifiedBy":2420,"ModifiedDate":"2015-09-30T19:45:52.22","DeletedBy":null,"DeletedDate":null,"RefID":null,"HelpMStorageServerId":null,"HelpMFilePath":null,"HelpMMineType":null,"HelpMFileLength":null,"HelpMCreateDate":null,"HelpMUpdateDate":null,"DetailType":"Major","ForSE":true,"ForQA":true,"IsMandatoryCapture":"Y"},{"DetailID":35220,"VersionNumber":1,"HeaderID":8586,"ScoreID":0,"SubjectID":null,"GroupName":"","DetailName":"ฝ้าเรียบไม่เห็นรอยต่อฝ้า,หัวน็อต,รอบดวงโคม(งานฝ้า)","Seq":1,"Status":null,"Remark":null,"CreatedBy":2420,"CreatedDate":"2015-09-30T19:45:52.22","ModifiedBy":2420,"ModifiedDate":"2015-09-30T19:45:52.22","DeletedBy":null,"DeletedDate":null,"RefID":null,"HelpMStorageServerId":null,"HelpMFilePath":null,"HelpMMineType":null,"HelpMFileLength":null,"HelpMCreateDate":null,"HelpMUpdateDate":null,"DetailType":"Major","ForSE":true,"ForQA":true,"IsMandatoryCapture":"Y"},{"DetailID":35221,"VersionNumber":1,"HeaderID":8586,"ScoreID":0,"SubjectID":null,"GroupName":"","DetailName":"ฝ้าไม่มีรอยร้าว(งานฝ้า)","Seq":2,"Status":null,"Remark":null,"CreatedBy":2420,"CreatedDate":"2015-09-30T19:45:52.22","ModifiedBy":2420,"ModifiedDate":"2015-09-30T19:45:52.22","DeletedBy":null,"DeletedDate":null,"RefID":null,"HelpMStorageServerId":null,"HelpMFilePath":null,"HelpMMineType":null,"HelpMFileLength":null,"HelpMCreateDate":null,"HelpMUpdateDate":null,"DetailType":"Major","ForSE":true,"ForQA":true,"IsMandatoryCapture":"Y"},{"DetailID":35222,"VersionNumber":1,"HeaderID":8586,"ScoreID":0,"SubjectID":null,"GroupName":"","DetailName":"สีฝ้าไม่ด่าง,เรียบสม่ำเสมอ(งานฝ้า)","Seq":3,"Status":null,"Remark":null,"CreatedBy":2420,"CreatedDate":"2015-09-30T19:45:52.22","ModifiedBy":2420,"ModifiedDate":"2015-09-30T19:45:52.22","DeletedBy":null,"DeletedDate":null,"RefID":null,"HelpMStorageServerId":null,"HelpMFilePath":null,"HelpMMineType":null,"HelpMFileLength":null,"HelpMCreateDate":null,"HelpMUpdateDate":null,"DetailType":"Major","ForSE":true,"ForQA":true,"IsMandatoryCapture":"Y"},{"DetailID":35223,"VersionNumber":1,"HeaderID":8587,"ScoreID":0,"SubjectID":null,"GroupName":"","DetailName":"เครื่องสำรองไฟใช้งานได้สมบูรณ์","Seq":1,"Status":null,"Remark":null,"CreatedBy":2420,"CreatedDate":"2015-09-30T19:45:52.22","ModifiedBy":2420,"ModifiedDate":"2015-09-30T19:45:52.22","DeletedBy":null,"DeletedDate":null,"RefID":null,"HelpMStorageServerId":null,"HelpMFilePath":null,"HelpMMineType":null,"HelpMFileLength":null,"HelpMCreateDate":null,"HelpMUpdateDate":null,"DetailType":"Major","ForSE":true,"ForQA":true,"IsMandatoryCapture":"Y"},{"DetailID":35224,"VersionNumber":1,"HeaderID":8588,"ScoreID":0,"SubjectID":null,"GroupName":"","DetailName":"ไม่มีน้ำขังพื้นส่วนแห้ง(ห้องน้ำ)","Seq":1,"Status":null,"Remark":null,"CreatedBy":2420,"CreatedDate":"2015-09-30T19:45:52.22","ModifiedBy":2420,"ModifiedDate":"2015-09-30T19:45:52.22","DeletedBy":null,"DeletedDate":null,"RefID":null,"HelpMStorageServerId":null,"HelpMFilePath":null,"HelpMMineType":null,"HelpMFileLength":null,"HelpMCreateDate":null,"HelpMUpdateDate":null,"DetailType":"Major","ForSE":true,"ForQA":true,"IsMandatoryCapture":"Y"},{"DetailID":35225,"VersionNumber":1,"HeaderID":8588,"ScoreID":0,"SubjectID":null,"GroupName":"","DetailName":"ไม่มีน้ำขังพื้นส่วนเปียก(ห้องน้ำ)","Seq":2,"Status":null,"Remark":null,"CreatedBy":2420,"CreatedDate":"2015-09-30T19:45:52.22","ModifiedBy":2420,"ModifiedDate":"2015-09-30T19:45:52.22","DeletedBy":null,"DeletedDate":null,"RefID":null,"HelpMStorageServerId":null,"HelpMFilePath":null,"HelpMMineType":null,"HelpMFileLength":null,"HelpMCreateDate":null,"HelpMUpdateDate":null,"DetailType":"Major","ForSE":true,"ForQA":true,"IsMandatoryCapture":"Y"},{"DetailID":35226,"VersionNumber":1,"HeaderID":8588,"ScoreID":0,"SubjectID":null,"GroupName":"","DetailName":"ทดสอบลูกปิงปองพื้นส่วนแห้งผ่าน(ห้องน้ำ)","Seq":3,"Status":null,"Remark":null,"CreatedBy":2420,"CreatedDate":"2015-09-30T19:45:52.22","ModifiedBy":2420,"ModifiedDate":"2015-09-30T19:45:52.22","DeletedBy":null,"DeletedDate":null,"RefID":null,"HelpMStorageServerId":null,"HelpMFilePath":null,"HelpMMineType":null,"HelpMFileLength":null,"HelpMCreateDate":null,"HelpMUpdateDate":null,"DetailType":"Major","ForSE":true,"ForQA":true,"IsMandatoryCapture":"Y"},{"DetailID":35227,"VersionNumber":1,"HeaderID":8588,"ScoreID":0,"SubjectID":null,"GroupName":"","DetailName":"ทดสอบลูกปิงปองพื้นส่วนเปียกผ่าน(ห้องน้ำ)","Seq":4,"Status":null,"Remark":null,"CreatedBy":2420,"CreatedDate":"2015-09-30T19:45:52.22","ModifiedBy":2420,"ModifiedDate":"2015-09-30T19:45:52.22","DeletedBy":null,"DeletedDate":null,"RefID":null,"HelpMStorageServerId":null,"HelpMFilePath":null,"HelpMMineType":null,"HelpMFileLength":null,"HelpMCreateDate":null,"HelpMUpdateDate":null,"DetailType":"Major","ForSE":true,"ForQA":true,"IsMandatoryCapture":"Y"},{"DetailID":35228,"VersionNumber":1,"HeaderID":8588,"ScoreID":0,"SubjectID":null,"GroupName":"","DetailName":"พิ้นไม่หลุดร่อน,พื้นไม่บิ่น,ร้าว,แตก(ห้องน้ำ)","Seq":5,"Status":null,"Remark":null,"CreatedBy":2420,"CreatedDate":"2015-09-30T19:45:52.22","ModifiedBy":2420,"ModifiedDate":"2015-09-30T19:45:52.22","DeletedBy":null,"DeletedDate":null,"RefID":null,"HelpMStorageServerId":null,"HelpMFilePath":null,"HelpMMineType":null,"HelpMFileLength":null,"HelpMCreateDate":null,"HelpMUpdateDate":null,"DetailType":"Major","ForSE":true,"ForQA":true,"IsMandatoryCapture":"Y"},{"DetailID":35229,"VersionNumber":1,"HeaderID":8588,"ScoreID":0,"SubjectID":null,"GroupName":"","DetailName":"พื้นไม่กระเดิด,พื้นสีไม่เพี้ยน,ยาแนวสม่ำเสมอ(ห้องน้ำ)","Seq":6,"Status":null,"Remark":null,"CreatedBy":2420,"CreatedDate":"2015-09-30T19:45:52.22","ModifiedBy":2420,"ModifiedDate":"2015-09-30T19:45:52.22","DeletedBy":null,"DeletedDate":null,"RefID":null,"HelpMStorageServerId":null,"HelpMFilePath":null,"HelpMMineType":null,"HelpMFileLength":null,"HelpMCreateDate":null,"HelpMUpdateDate":null,"DetailType":"Major","ForSE":true,"ForQA":true,"IsMandatoryCapture":"Y"},{"DetailID":35230,"VersionNumber":1,"HeaderID":8588,"ScoreID":0,"SubjectID":null,"GroupName":"","DetailName":"ติดตั้งอุปกรณ์ครบถ้วน(อ้างล้างหน้า,กระจกเงา,ฝักบัว,สายฉีด)(ห้องน้ำ)","Seq":7,"Status":null,"Remark":null,"CreatedBy":2420,"CreatedDate":"2015-09-30T19:45:52.22","ModifiedBy":2420,"ModifiedDate":"2015-09-30T19:45:52.22","DeletedBy":null,"DeletedDate":null,"RefID":null,"HelpMStorageServerId":null,"HelpMFilePath":null,"HelpMMineType":null,"HelpMFileLength":null,"HelpMCreateDate":null,"HelpMUpdateDate":null,"DetailType":"Major","ForSE":true,"ForQA":true,"IsMandatoryCapture":"Y"},{"DetailID":35231,"VersionNumber":1,"HeaderID":8589,"ScoreID":0,"SubjectID":null,"GroupName":"","DetailName":"ติดตั้ง Cercuit Breaker  ถูกต้อง,ครบถ้วน(ตู้ Main Breaker)","Seq":1,"Status":null,"Remark":null,"CreatedBy":2420,"CreatedDate":"2015-09-30T19:45:52.22","ModifiedBy":2420,"ModifiedDate":"2015-09-30T19:45:52.22","DeletedBy":null,"DeletedDate":null,"RefID":null,"HelpMStorageServerId":null,"HelpMFilePath":null,"HelpMMineType":null,"HelpMFileLength":null,"HelpMCreateDate":null,"HelpMUpdateDate":null,"DetailType":"Major","ForSE":true,"ForQA":true,"IsMandatoryCapture":"Y"},{"DetailID":35232,"VersionNumber":1,"HeaderID":8589,"ScoreID":0,"SubjectID":null,"GroupName":"","DetailName":"ติดป้ายหน้าที่ Breaker ถูกต้อง,ครบถ้วน(ตู้ Main Breaker)","Seq":2,"Status":null,"Remark":null,"CreatedBy":2420,"CreatedDate":"2015-09-30T19:45:52.22","ModifiedBy":2420,"ModifiedDate":"2015-09-30T19:45:52.22","DeletedBy":null,"DeletedDate":null,"RefID":null,"HelpMStorageServerId":null,"HelpMFilePath":null,"HelpMMineType":null,"HelpMFileLength":null,"HelpMCreateDate":null,"HelpMUpdateDate":null,"DetailType":"Major","ForSE":true,"ForQA":true,"IsMandatoryCapture":"Y"},{"DetailID":35233,"VersionNumber":1,"HeaderID":8590,"ScoreID":0,"SubjectID":null,"GroupName":"","DetailName":"ขนาดสระว่ายน้ำ","Seq":1,"Status":null,"Remark":null,"CreatedBy":2420,"CreatedDate":"2015-09-30T19:45:52.22","ModifiedBy":2420,"ModifiedDate":"2015-09-30T19:45:52.22","DeletedBy":null,"DeletedDate":null,"RefID":null,"HelpMStorageServerId":null,"HelpMFilePath":null,"HelpMMineType":null,"HelpMFileLength":null,"HelpMCreateDate":null,"HelpMUpdateDate":null,"DetailType":"Major","ForSE":true,"ForQA":true,"IsMandatoryCapture":"Y"},{"DetailID":35234,"VersionNumber":1,"HeaderID":8590,"ScoreID":0,"SubjectID":null,"GroupName":"","DetailName":"ระบบปั๊มน้ำต่างๆ","Seq":2,"Status":null,"Remark":null,"CreatedBy":2420,"CreatedDate":"2015-09-30T19:45:52.22","ModifiedBy":2420,"ModifiedDate":"2015-09-30T19:45:52.22","DeletedBy":null,"DeletedDate":null,"RefID":null,"HelpMStorageServerId":null,"HelpMFilePath":null,"HelpMMineType":null,"HelpMFileLength":null,"HelpMCreateDate":null,"HelpMUpdateDate":null,"DetailType":"Major","ForSE":true,"ForQA":true,"IsMandatoryCapture":"Y"},{"DetailID":35235,"VersionNumber":1,"HeaderID":8590,"ScoreID":0,"SubjectID":null,"GroupName":"","DetailName":"ยาแนวกระเบื่อง","Seq":3,"Status":null,"Remark":null,"CreatedBy":2420,"CreatedDate":"2015-09-30T19:45:52.22","ModifiedBy":2420,"ModifiedDate":"2015-09-30T19:45:52.22","DeletedBy":null,"DeletedDate":null,"RefID":null,"HelpMStorageServerId":null,"HelpMFilePath":null,"HelpMMineType":null,"HelpMFileLength":null,"HelpMCreateDate":null,"HelpMUpdateDate":null,"DetailType":"Major","ForSE":true,"ForQA":true,"IsMandatoryCapture":"Y"},{"DetailID":35236,"VersionNumber":1,"HeaderID":8590,"ScoreID":0,"SubjectID":null,"GroupName":"","DetailName":"กระเบื่องไม่บิ่น,แตก","Seq":4,"Status":null,"Remark":null,"CreatedBy":2420,"CreatedDate":"2015-09-30T19:45:52.22","ModifiedBy":2420,"ModifiedDate":"2015-09-30T19:45:52.22","DeletedBy":null,"DeletedDate":null,"RefID":null,"HelpMStorageServerId":null,"HelpMFilePath":null,"HelpMMineType":null,"HelpMFileLength":null,"HelpMCreateDate":null,"HelpMUpdateDate":null,"DetailType":"Major","ForSE":true,"ForQA":true,"IsMandatoryCapture":"Y"},{"DetailID":35237,"VersionNumber":1,"HeaderID":8590,"ScoreID":0,"SubjectID":null,"GroupName":"","DetailName":"ที่ล้างตัวก่อนลงสระใช้งานได้","Seq":5,"Status":null,"Remark":null,"CreatedBy":2420,"CreatedDate":"2015-09-30T19:45:52.22","ModifiedBy":2420,"ModifiedDate":"2015-09-30T19:45:52.22","DeletedBy":null,"DeletedDate":null,"RefID":null,"HelpMStorageServerId":null,"HelpMFilePath":null,"HelpMMineType":null,"HelpMFileLength":null,"HelpMCreateDate":null,"HelpMUpdateDate":null,"DetailType":"Major","ForSE":true,"ForQA":true,"IsMandatoryCapture":"Y"},{"DetailID":35238,"VersionNumber":1,"HeaderID":8591,"ScoreID":0,"SubjectID":null,"GroupName":"","DetailName":"เติมน้ำสะอาดให้เต็มสระ และทิ้งไว้ 24 ชั่วโมง","Seq":1,"Status":null,"Remark":null,"CreatedBy":2420,"CreatedDate":"2015-09-30T19:45:52.22","ModifiedBy":2420,"ModifiedDate":"2015-09-30T19:45:52.22","DeletedBy":null,"DeletedDate":null,"RefID":null,"HelpMStorageServerId":null,"HelpMFilePath":null,"HelpMMineType":null,"HelpMFileLength":null,"HelpMCreateDate":null,"HelpMUpdateDate":null,"DetailType":"Major","ForSE":true,"ForQA":true,"IsMandatoryCapture":"Y"},{"DetailID":35239,"VersionNumber":1,"HeaderID":8591,"ScoreID":0,"SubjectID":null,"GroupName":"","DetailName":"ทดสอบระบบ ปั๊มน้ำ สระว่ายน้ำ ,ระบบกรองน้ำ","Seq":2,"Status":null,"Remark":null,"CreatedBy":2420,"CreatedDate":"2015-09-30T19:45:52.22","ModifiedBy":2420,"ModifiedDate":"2015-09-30T19:45:52.22","DeletedBy":null,"DeletedDate":null,"RefID":null,"HelpMStorageServerId":null,"HelpMFilePath":null,"HelpMMineType":null,"HelpMFileLength":null,"HelpMCreateDate":null,"HelpMUpdateDate":null,"DetailType":"Major","ForSE":true,"ForQA":true,"IsMandatoryCapture":"Y"},{"DetailID":35240,"VersionNumber":1,"HeaderID":8591,"ScoreID":0,"SubjectID":null,"GroupName":"","DetailName":"ทดสอบระบบไฟฟ้าใต้น้ำ","Seq":3,"Status":null,"Remark":null,"CreatedBy":2420,"CreatedDate":"2015-09-30T19:45:52.22","ModifiedBy":2420,"ModifiedDate":"2015-09-30T19:45:52.22","DeletedBy":null,"DeletedDate":null,"RefID":null,"HelpMStorageServerId":null,"HelpMFilePath":null,"HelpMMineType":null,"HelpMFileLength":null,"HelpMCreateDate":null,"HelpMUpdateDate":null,"DetailType":"Major","ForSE":true,"ForQA":true,"IsMandatoryCapture":"Y"}],"LastSyncDate":"0001-01-01T00:00:00","DataRelatedChangeCode":"daba82fc-1cf6-438a-aac8-c019da8c7600"}
