{"ProjectModelId":"P147_96","ProjectID":147,"ProjectName":"โครงการ Train","ModelID":96,"ModelName":"20118-400001_งานสโมสร+สระว่ายน้ำ งวดที่ 1","FModel":{"ModelID":96,"ModelCode":null,"ModelName":"20118-400001_งานสโมสร+สระว่ายน้ำ งวดที่ 1","ModelType":"F","ModelTypeName":"สาธาฯ","CreatedBy":5272,"CreatedByName":"นางสาวธีรนันท์ กรศรีทิพา","CreatedDate":"2015-09-30T18:54:49.607","ModifiedBy":5272,"ModifiedByName":"นางสาวธีรนันท์ กรศรีทิพา","ModifiedDate":"2015-09-30T18:54:49.607","DataRelatedChangeCode":"f54d0203-ac9c-4ce1-826e-97351d3531fe","PartialEndProduct":false,"PartialEndProductName":"N"},"FPhases":[{"ModelID":96,"ModelCode":null,"ModelName":"20118-400001_งานสโมสร+สระว่ายน้ำ งวดที่ 1","ModelType":"F","ModelTypeName":"สาธาฯ","PhaseID":684,"PhaseName":"งานเสาเข็ม สโมสร","PhaseSeq":1,"PhaseType":"2","Progress":15.00,"UseOnStartProgress":null,"UseOnFinishProgress":null,"UseOnFinish":null,"CreatedBy":2420,"CreatedByName":"นายหฤษฎ์ เวชากุล","CreatedDate":"2015-09-30T19:40:57.253","ModifiedBy":2420,"ModifiedByName":"นายหฤษฎ์ เวชากุล","ModifiedDate":"2015-09-30T19:40:57.253","DeletedBy":null,"DeletedDate":null,"PlanProcessDay":15},{"ModelID":96,"ModelCode":null,"ModelName":"20118-400001_งานสโมสร+สระว่ายน้ำ งวดที่ 1","ModelType":"F","ModelTypeName":"สาธาฯ","PhaseID":685,"PhaseName":"ขออนุมัติเทคอนกรีตฐานราก","PhaseSeq":2,"PhaseType":"2","Progress":15.00,"UseOnStartProgress":null,"UseOnFinishProgress":null,"UseOnFinish":null,"CreatedBy":2420,"CreatedByName":"นายหฤษฎ์ เวชากุล","CreatedDate":"2015-09-30T19:40:57.253","ModifiedBy":2420,"ModifiedByName":"นายหฤษฎ์ เวชากุล","ModifiedDate":"2015-09-30T19:40:57.253","DeletedBy":null,"DeletedDate":null,"PlanProcessDay":15},{"ModelID":96,"ModelCode":null,"ModelName":"20118-400001_งานสโมสร+สระว่ายน้ำ งวดที่ 1","ModelType":"F","ModelTypeName":"สาธาฯ","PhaseID":686,"PhaseName":"ขออนุมัติเทคอนกรีต  คสล.คานคอดิน","PhaseSeq":2,"PhaseType":"2","Progress":15.00,"UseOnStartProgress":null,"UseOnFinishProgress":null,"UseOnFinish":null,"CreatedBy":2420,"CreatedByName":"นายหฤษฎ์ เวชากุล","CreatedDate":"2015-09-30T19:40:57.253","ModifiedBy":2420,"ModifiedByName":"นายหฤษฎ์ เวชากุล","ModifiedDate":"2015-09-30T19:40:57.253","DeletedBy":null,"DeletedDate":null,"PlanProcessDay":15},{"ModelID":96,"ModelCode":null,"ModelName":"20118-400001_งานสโมสร+สระว่ายน้ำ งวดที่ 1","ModelType":"F","ModelTypeName":"สาธาฯ","PhaseID":687,"PhaseName":"วางพื้นชั้น1 และเทคสล.ทับหน้าพื้นชั้น 1","PhaseSeq":3,"PhaseType":"2","Progress":15.00,"UseOnStartProgress":null,"UseOnFinishProgress":null,"UseOnFinish":null,"CreatedBy":2420,"CreatedByName":"นายหฤษฎ์ เวชากุล","CreatedDate":"2015-09-30T19:40:57.253","ModifiedBy":2420,"ModifiedByName":"นายหฤษฎ์ เวชากุล","ModifiedDate":"2015-09-30T19:40:57.253","DeletedBy":null,"DeletedDate":null,"PlanProcessDay":15},{"ModelID":96,"ModelCode":null,"ModelName":"20118-400001_งานสโมสร+สระว่ายน้ำ งวดที่ 1","ModelType":"F","ModelTypeName":"สาธาฯ","PhaseID":688,"PhaseName":"ขออนุมัติเทคอนกรีตคสล.เสาชั้น 1","PhaseSeq":3,"PhaseType":"2","Progress":15.00,"UseOnStartProgress":null,"UseOnFinishProgress":null,"UseOnFinish":null,"CreatedBy":2420,"CreatedByName":"นายหฤษฎ์ เวชากุล","CreatedDate":"2015-09-30T19:40:57.253","ModifiedBy":2420,"ModifiedByName":"นายหฤษฎ์ เวชากุล","ModifiedDate":"2015-09-30T19:40:57.253","DeletedBy":null,"DeletedDate":null,"PlanProcessDay":15}],"FHeaders":[{"ModelID":96,"ModelCode":null,"ModelName":"20118-400001_งานสโมสร+สระว่ายน้ำ งวดที่ 1","ModelType":"F","ModelTypeName":"สาธาฯ","PhaseID":684,"PhaseName":"งานเสาเข็ม สโมสร","PhaseSeq":1,"PhaseType":"2","Progress":15.00,"HeaderID":8490,"HeaderVersionNumber":1,"HeaderName":"รายละเอียดงาน","HeaderType":"REQ","HeaderSeq":1,"ForSe":true,"ForQA":false,"ForQAName":"N","HeaderRemark":null,"AreaID":0,"AreaName":"","CreatedBy":2420,"CreatedByName":"นายหฤษฎ์ เวชากุล","CreatedDate":"2015-09-30T19:40:57.253","ModifiedBy":2420,"ModifiedByName":"นายหฤษฎ์ เวชากุล","ModifiedDate":"2015-09-30T19:40:57.253","GroupID":0,"GroupName":null,"DeletedBy":null,"DeletedDate":null,"IsMandatoryCapture":"N"},{"ModelID":96,"ModelCode":null,"ModelName":"20118-400001_งานสโมสร+สระว่ายน้ำ งวดที่ 1","ModelType":"F","ModelTypeName":"สาธาฯ","PhaseID":685,"PhaseName":"ขออนุมัติเทคอนกรีตฐานราก","PhaseSeq":2,"PhaseType":"2","Progress":15.00,"HeaderID":8491,"HeaderVersionNumber":1,"HeaderName":"รายละเอียดงาน","HeaderType":"REQ","HeaderSeq":1,"ForSe":true,"ForQA":true,"ForQAName":"Y","HeaderRemark":null,"AreaID":0,"AreaName":"","CreatedBy":2420,"CreatedByName":"นายหฤษฎ์ เวชากุล","CreatedDate":"2015-09-30T19:40:57.253","ModifiedBy":2420,"ModifiedByName":"นายหฤษฎ์ เวชากุล","ModifiedDate":"2015-09-30T19:40:57.253","GroupID":0,"GroupName":null,"DeletedBy":null,"DeletedDate":null,"IsMandatoryCapture":"Y"},{"ModelID":96,"ModelCode":null,"ModelName":"20118-400001_งานสโมสร+สระว่ายน้ำ งวดที่ 1","ModelType":"F","ModelTypeName":"สาธาฯ","PhaseID":686,"PhaseName":"ขออนุมัติเทคอนกรีต  คสล.คานคอดิน","PhaseSeq":2,"PhaseType":"2","Progress":15.00,"HeaderID":8492,"HeaderVersionNumber":1,"HeaderName":"รายละเอียดงาน","HeaderType":"REQ","HeaderSeq":1,"ForSe":true,"ForQA":true,"ForQAName":"Y","HeaderRemark":null,"AreaID":0,"AreaName":"","CreatedBy":2420,"CreatedByName":"นายหฤษฎ์ เวชากุล","CreatedDate":"2015-09-30T19:40:57.253","ModifiedBy":2420,"ModifiedByName":"นายหฤษฎ์ เวชากุล","ModifiedDate":"2015-09-30T19:40:57.253","GroupID":0,"GroupName":null,"DeletedBy":null,"DeletedDate":null,"IsMandatoryCapture":"Y"},{"ModelID":96,"ModelCode":null,"ModelName":"20118-400001_งานสโมสร+สระว่ายน้ำ งวดที่ 1","ModelType":"F","ModelTypeName":"สาธาฯ","PhaseID":687,"PhaseName":"วางพื้นชั้น1 และเทคสล.ทับหน้าพื้นชั้น 1","PhaseSeq":3,"PhaseType":"2","Progress":15.00,"HeaderID":8493,"HeaderVersionNumber":1,"HeaderName":"รายละเอียดงาน","HeaderType":"REQ","HeaderSeq":1,"ForSe":true,"ForQA":false,"ForQAName":"N","HeaderRemark":null,"AreaID":0,"AreaName":"","CreatedBy":2420,"CreatedByName":"นายหฤษฎ์ เวชากุล","CreatedDate":"2015-09-30T19:40:57.253","ModifiedBy":2420,"ModifiedByName":"นายหฤษฎ์ เวชากุล","ModifiedDate":"2015-09-30T19:40:57.253","GroupID":0,"GroupName":null,"DeletedBy":null,"DeletedDate":null,"IsMandatoryCapture":"N"},{"ModelID":96,"ModelCode":null,"ModelName":"20118-400001_งานสโมสร+สระว่ายน้ำ งวดที่ 1","ModelType":"F","ModelTypeName":"สาธาฯ","PhaseID":688,"PhaseName":"ขออนุมัติเทคอนกรีตคสล.เสาชั้น 1","PhaseSeq":3,"PhaseType":"2","Progress":15.00,"HeaderID":8494,"HeaderVersionNumber":1,"HeaderName":"รายละเอียดงาน","HeaderType":"REQ","HeaderSeq":1,"ForSe":true,"ForQA":false,"ForQAName":"N","HeaderRemark":null,"AreaID":0,"AreaName":"","CreatedBy":2420,"CreatedByName":"นายหฤษฎ์ เวชากุล","CreatedDate":"2015-09-30T19:40:57.253","ModifiedBy":2420,"ModifiedByName":"นายหฤษฎ์ เวชากุล","ModifiedDate":"2015-09-30T19:40:57.253","GroupID":0,"GroupName":null,"DeletedBy":null,"DeletedDate":null,"IsMandatoryCapture":"N"}],"FDetails":[{"DetailID":34831,"VersionNumber":1,"HeaderID":8494,"ScoreID":0,"SubjectID":null,"GroupName":"","DetailName":"มีไม้ล็อคปลายเหล็กกันเคลื่อนแน่นหนา","Seq":3,"Status":null,"Remark":null,"CreatedBy":2420,"CreatedDate":"2015-09-30T19:40:57.253","ModifiedBy":2420,"ModifiedDate":"2015-09-30T19:40:57.253","DeletedBy":null,"DeletedDate":null,"RefID":null,"HelpMStorageServerId":null,"HelpMFilePath":null,"HelpMMineType":null,"HelpMFileLength":null,"HelpMCreateDate":null,"HelpMUpdateDate":null,"DetailType":"Major","ForSE":true,"ForQA":false,"IsMandatoryCapture":"N"},{"DetailID":34806,"VersionNumber":1,"HeaderID":8490,"ScoreID":0,"SubjectID":null,"GroupName":"","DetailName":"หน้าตัด,ความยาวเสาเข็มตามแบบ","Seq":1,"Status":null,"Remark":null,"CreatedBy":2420,"CreatedDate":"2015-09-30T19:40:57.253","ModifiedBy":2420,"ModifiedDate":"2015-09-30T19:40:57.253","DeletedBy":null,"DeletedDate":null,"RefID":null,"HelpMStorageServerId":null,"HelpMFilePath":null,"HelpMMineType":null,"HelpMFileLength":null,"HelpMCreateDate":null,"HelpMUpdateDate":null,"DetailType":"Major","ForSE":true,"ForQA":false,"IsMandatoryCapture":"N"},{"DetailID":34807,"VersionNumber":1,"HeaderID":8490,"ScoreID":0,"SubjectID":null,"GroupName":"","DetailName":"เข็มไม่มีรอยร้าวยาว>20cm,ลึก>4cm","Seq":2,"Status":null,"Remark":null,"CreatedBy":2420,"CreatedDate":"2015-09-30T19:40:57.253","ModifiedBy":2420,"ModifiedDate":"2015-09-30T19:40:57.253","DeletedBy":null,"DeletedDate":null,"RefID":null,"HelpMStorageServerId":null,"HelpMFilePath":null,"HelpMMineType":null,"HelpMFileLength":null,"HelpMCreateDate":null,"HelpMUpdateDate":null,"DetailType":"Major","ForSE":true,"ForQA":false,"IsMandatoryCapture":"N"},{"DetailID":34808,"VersionNumber":1,"HeaderID":8490,"ScoreID":0,"SubjectID":null,"GroupName":"","DetailName":"มีรายการคำนวณ Bloe count,ระยะยกและน้ำหนักตุ้ม","Seq":3,"Status":null,"Remark":null,"CreatedBy":2420,"CreatedDate":"2015-09-30T19:40:57.253","ModifiedBy":2420,"ModifiedDate":"2015-09-30T19:40:57.253","DeletedBy":null,"DeletedDate":null,"RefID":null,"HelpMStorageServerId":null,"HelpMFilePath":null,"HelpMMineType":null,"HelpMFileLength":null,"HelpMCreateDate":null,"HelpMUpdateDate":null,"DetailType":"Major","ForSE":true,"ForQA":false,"IsMandatoryCapture":"N"},{"DetailID":34809,"VersionNumber":1,"HeaderID":8490,"ScoreID":0,"SubjectID":null,"GroupName":"","DetailName":"ตำแหน่งหมุดพ่นสีแยกตามขนาดเข็มถูกต้องแข็งแรง","Seq":4,"Status":null,"Remark":null,"CreatedBy":2420,"CreatedDate":"2015-09-30T19:40:57.253","ModifiedBy":2420,"ModifiedDate":"2015-09-30T19:40:57.253","DeletedBy":null,"DeletedDate":null,"RefID":null,"HelpMStorageServerId":null,"HelpMFilePath":null,"HelpMMineType":null,"HelpMFileLength":null,"HelpMCreateDate":null,"HelpMUpdateDate":null,"DetailType":"Major","ForSE":true,"ForQA":false,"IsMandatoryCapture":"N"},{"DetailID":34810,"VersionNumber":1,"HeaderID":8491,"ScoreID":0,"SubjectID":null,"GroupName":"","DetailName":"ตรวจสอบค่า Pile Deviation ทุกต้นและแจ้งต่อวิศวกรหน่วยงานเพื่อพิจารณาแล้ว","Seq":1,"Status":null,"Remark":null,"CreatedBy":2420,"CreatedDate":"2015-09-30T19:40:57.253","ModifiedBy":2420,"ModifiedDate":"2015-09-30T19:40:57.253","DeletedBy":null,"DeletedDate":null,"RefID":null,"HelpMStorageServerId":null,"HelpMFilePath":null,"HelpMMineType":null,"HelpMFileLength":null,"HelpMCreateDate":null,"HelpMUpdateDate":null,"DetailType":"Major","ForSE":true,"ForQA":true,"IsMandatoryCapture":"Y"},{"DetailID":34811,"VersionNumber":1,"HeaderID":8491,"ScoreID":0,"SubjectID":null,"GroupName":"","DetailName":"เสาเข็มทุกต้น ผ่านการทดสอบ Seismic Test และสามารถใช้งานได้","Seq":2,"Status":null,"Remark":null,"CreatedBy":2420,"CreatedDate":"2015-09-30T19:40:57.253","ModifiedBy":2420,"ModifiedDate":"2015-09-30T19:40:57.253","DeletedBy":null,"DeletedDate":null,"RefID":null,"HelpMStorageServerId":null,"HelpMFilePath":null,"HelpMMineType":null,"HelpMFileLength":null,"HelpMCreateDate":null,"HelpMUpdateDate":null,"DetailType":"Major","ForSE":true,"ForQA":true,"IsMandatoryCapture":"Y"},{"DetailID":34812,"VersionNumber":1,"HeaderID":8491,"ScoreID":0,"SubjectID":null,"GroupName":"","DetailName":"หัวเสาเข็มที่สกัดไม่แตก บิ่น ได้ระดับสม่ำอมในฐานราก7 - 10 cm","Seq":3,"Status":null,"Remark":null,"CreatedBy":2420,"CreatedDate":"2015-09-30T19:40:57.253","ModifiedBy":2420,"ModifiedDate":"2015-09-30T19:40:57.253","DeletedBy":null,"DeletedDate":null,"RefID":null,"HelpMStorageServerId":null,"HelpMFilePath":null,"HelpMMineType":null,"HelpMFileLength":null,"HelpMCreateDate":null,"HelpMUpdateDate":null,"DetailType":"Major","ForSE":true,"ForQA":true,"IsMandatoryCapture":"Y"},{"DetailID":34813,"VersionNumber":1,"HeaderID":8491,"ScoreID":0,"SubjectID":null,"GroupName":"","DetailName":"แบบหล่อขนาด,ระดับเทถูกต้องแข็งแรง รอยต่อแนบสนิททุกด้าน","Seq":4,"Status":null,"Remark":null,"CreatedBy":2420,"CreatedDate":"2015-09-30T19:40:57.253","ModifiedBy":2420,"ModifiedDate":"2015-09-30T19:40:57.253","DeletedBy":null,"DeletedDate":null,"RefID":null,"HelpMStorageServerId":null,"HelpMFilePath":null,"HelpMMineType":null,"HelpMFileLength":null,"HelpMCreateDate":null,"HelpMUpdateDate":null,"DetailType":"Major","ForSE":true,"ForQA":true,"IsMandatoryCapture":"Y"},{"DetailID":34814,"VersionNumber":1,"HeaderID":8491,"ScoreID":0,"SubjectID":null,"GroupName":"","DetailName":"ติดตั้งเหล็กเสริมต่างๆถูกต้องทั้งขนาด จำนวน ระยะห่าง","Seq":5,"Status":null,"Remark":null,"CreatedBy":2420,"CreatedDate":"2015-09-30T19:40:57.253","ModifiedBy":2420,"ModifiedDate":"2015-09-30T19:40:57.253","DeletedBy":null,"DeletedDate":null,"RefID":null,"HelpMStorageServerId":null,"HelpMFilePath":null,"HelpMMineType":null,"HelpMFileLength":null,"HelpMCreateDate":null,"HelpMUpdateDate":null,"DetailType":"Major","ForSE":true,"ForQA":true,"IsMandatoryCapture":"Y"},{"DetailID":34815,"VersionNumber":1,"HeaderID":8491,"ScoreID":0,"SubjectID":null,"GroupName":"","DetailName":"เหล็กเสริมเสาตอม่อถูกต้องทั้งขนาด จำนวน ตำแหน่ง  และระยะของศูนย์เสา","Seq":6,"Status":null,"Remark":null,"CreatedBy":2420,"CreatedDate":"2015-09-30T19:40:57.253","ModifiedBy":2420,"ModifiedDate":"2015-09-30T19:40:57.253","DeletedBy":null,"DeletedDate":null,"RefID":null,"HelpMStorageServerId":null,"HelpMFilePath":null,"HelpMMineType":null,"HelpMFileLength":null,"HelpMCreateDate":null,"HelpMUpdateDate":null,"DetailType":"Major","ForSE":true,"ForQA":true,"IsMandatoryCapture":"Y"},{"DetailID":34816,"VersionNumber":1,"HeaderID":8491,"ScoreID":0,"SubjectID":null,"GroupName":"","DetailName":"ตรวจสอบระยะร่น, ขนาดอาคารClub House ตรงตามผังจัดสรร","Seq":7,"Status":null,"Remark":null,"CreatedBy":2420,"CreatedDate":"2015-09-30T19:40:57.253","ModifiedBy":2420,"ModifiedDate":"2015-09-30T19:40:57.253","DeletedBy":null,"DeletedDate":null,"RefID":null,"HelpMStorageServerId":null,"HelpMFilePath":null,"HelpMMineType":null,"HelpMFileLength":null,"HelpMCreateDate":null,"HelpMUpdateDate":null,"DetailType":"Major","ForSE":true,"ForQA":true,"IsMandatoryCapture":"Y"},{"DetailID":34817,"VersionNumber":1,"HeaderID":8492,"ScoreID":0,"SubjectID":null,"GroupName":"","DetailName":"แบบหล่อคอนกรีตติดตั้งได้มั่นคงแข็งแรง รอยต่อแบบต้องแนบสนิทกันทุกด้าน","Seq":1,"Status":null,"Remark":null,"CreatedBy":2420,"CreatedDate":"2015-09-30T19:40:57.253","ModifiedBy":2420,"ModifiedDate":"2015-09-30T19:40:57.253","DeletedBy":null,"DeletedDate":null,"RefID":null,"HelpMStorageServerId":null,"HelpMFilePath":null,"HelpMMineType":null,"HelpMFileLength":null,"HelpMCreateDate":null,"HelpMUpdateDate":null,"DetailType":"Major","ForSE":true,"ForQA":true,"IsMandatoryCapture":"Y"},{"DetailID":34818,"VersionNumber":1,"HeaderID":8492,"ScoreID":0,"SubjectID":null,"GroupName":"","DetailName":"ติดตั้งเหล็กเสริมต่างๆถูกต้องทั้งขนาด จำนวน ระยะห่างโดยผูกยึดไว้อย่างแข็งแรง","Seq":2,"Status":null,"Remark":null,"CreatedBy":2420,"CreatedDate":"2015-09-30T19:40:57.253","ModifiedBy":2420,"ModifiedDate":"2015-09-30T19:40:57.253","DeletedBy":null,"DeletedDate":null,"RefID":null,"HelpMStorageServerId":null,"HelpMFilePath":null,"HelpMMineType":null,"HelpMFileLength":null,"HelpMCreateDate":null,"HelpMUpdateDate":null,"DetailType":"Major","ForSE":true,"ForQA":true,"IsMandatoryCapture":"Y"},{"DetailID":34819,"VersionNumber":1,"HeaderID":8492,"ScoreID":0,"SubjectID":null,"GroupName":"","DetailName":"คานติดดินลูกปูน5 cm ,คานลอยลูกปูน2.5cm ยึดกับเหล็กเสริมแข็งแรงและเพียงพอ","Seq":3,"Status":null,"Remark":null,"CreatedBy":2420,"CreatedDate":"2015-09-30T19:40:57.253","ModifiedBy":2420,"ModifiedDate":"2015-09-30T19:40:57.253","DeletedBy":null,"DeletedDate":null,"RefID":null,"HelpMStorageServerId":null,"HelpMFilePath":null,"HelpMMineType":null,"HelpMFileLength":null,"HelpMCreateDate":null,"HelpMUpdateDate":null,"DetailType":"Major","ForSE":true,"ForQA":true,"IsMandatoryCapture":"Y"},{"DetailID":34820,"VersionNumber":1,"HeaderID":8492,"ScoreID":0,"SubjectID":null,"GroupName":"","DetailName":"วาง Sleeves ท่อพร้อมเหล็กเสริมถูกต้องและครบถ้วน","Seq":4,"Status":null,"Remark":null,"CreatedBy":2420,"CreatedDate":"2015-09-30T19:40:57.253","ModifiedBy":2420,"ModifiedDate":"2015-09-30T19:40:57.253","DeletedBy":null,"DeletedDate":null,"RefID":null,"HelpMStorageServerId":null,"HelpMFilePath":null,"HelpMMineType":null,"HelpMFileLength":null,"HelpMCreateDate":null,"HelpMUpdateDate":null,"DetailType":"Major","ForSE":true,"ForQA":true,"IsMandatoryCapture":"Y"},{"DetailID":34821,"VersionNumber":1,"HeaderID":8493,"ScoreID":0,"SubjectID":null,"GroupName":"","DetailName":"หล่อหูช้างคสล. รับแผ่นพื้นฯครบถ้วนและถูกต้องตามมาตรฐาน","Seq":1,"Status":null,"Remark":null,"CreatedBy":2420,"CreatedDate":"2015-09-30T19:40:57.253","ModifiedBy":2420,"ModifiedDate":"2015-09-30T19:40:57.253","DeletedBy":null,"DeletedDate":null,"RefID":null,"HelpMStorageServerId":null,"HelpMFilePath":null,"HelpMMineType":null,"HelpMFileLength":null,"HelpMCreateDate":null,"HelpMUpdateDate":null,"DetailType":"Major","ForSE":true,"ForQA":false,"IsMandatoryCapture":"N"},{"DetailID":34822,"VersionNumber":1,"HeaderID":8493,"ScoreID":0,"SubjectID":null,"GroupName":"","DetailName":"เตรียมเหล็กเสริมยึดข้างแผ่นและหัวแผ่นรอบกรอบ","Seq":2,"Status":null,"Remark":null,"CreatedBy":2420,"CreatedDate":"2015-09-30T19:40:57.253","ModifiedBy":2420,"ModifiedDate":"2015-09-30T19:40:57.253","DeletedBy":null,"DeletedDate":null,"RefID":null,"HelpMStorageServerId":null,"HelpMFilePath":null,"HelpMMineType":null,"HelpMFileLength":null,"HelpMCreateDate":null,"HelpMUpdateDate":null,"DetailType":"Major","ForSE":true,"ForQA":false,"IsMandatoryCapture":"N"},{"DetailID":34823,"VersionNumber":1,"HeaderID":8493,"ScoreID":0,"SubjectID":null,"GroupName":"","DetailName":"ระบบป้องกันปลวกติดตั้งถูกต้องตามมาตรฐาน","Seq":3,"Status":null,"Remark":null,"CreatedBy":2420,"CreatedDate":"2015-09-30T19:40:57.253","ModifiedBy":2420,"ModifiedDate":"2015-09-30T19:40:57.253","DeletedBy":null,"DeletedDate":null,"RefID":null,"HelpMStorageServerId":null,"HelpMFilePath":null,"HelpMMineType":null,"HelpMFileLength":null,"HelpMCreateDate":null,"HelpMUpdateDate":null,"DetailType":"Major","ForSE":true,"ForQA":false,"IsMandatoryCapture":"N"},{"DetailID":34824,"VersionNumber":1,"HeaderID":8493,"ScoreID":0,"SubjectID":null,"GroupName":"","DetailName":"ติดตั้งเหล็กเสริมหัวแผ่นตามมาตรฐาน","Seq":4,"Status":null,"Remark":null,"CreatedBy":2420,"CreatedDate":"2015-09-30T19:40:57.253","ModifiedBy":2420,"ModifiedDate":"2015-09-30T19:40:57.253","DeletedBy":null,"DeletedDate":null,"RefID":null,"HelpMStorageServerId":null,"HelpMFilePath":null,"HelpMMineType":null,"HelpMFileLength":null,"HelpMCreateDate":null,"HelpMUpdateDate":null,"DetailType":"Major","ForSE":true,"ForQA":false,"IsMandatoryCapture":"N"},{"DetailID":34825,"VersionNumber":1,"HeaderID":8493,"ScoreID":0,"SubjectID":null,"GroupName":"","DetailName":"ติดตั้งเหล็กเสริมยึดระหว่างแผ่นพร้อมเชื่อมตามมาตรฐาน","Seq":5,"Status":null,"Remark":null,"CreatedBy":2420,"CreatedDate":"2015-09-30T19:40:57.253","ModifiedBy":2420,"ModifiedDate":"2015-09-30T19:40:57.253","DeletedBy":null,"DeletedDate":null,"RefID":null,"HelpMStorageServerId":null,"HelpMFilePath":null,"HelpMMineType":null,"HelpMFileLength":null,"HelpMCreateDate":null,"HelpMUpdateDate":null,"DetailType":"Major","ForSE":true,"ForQA":false,"IsMandatoryCapture":"N"},{"DetailID":34826,"VersionNumber":1,"HeaderID":8493,"ScoreID":0,"SubjectID":null,"GroupName":"","DetailName":"ติดตั้งเหล็กเสริมข้างและหัวแผ่นที่คานนอกตามมาตรฐาน","Seq":6,"Status":null,"Remark":null,"CreatedBy":2420,"CreatedDate":"2015-09-30T19:40:57.253","ModifiedBy":2420,"ModifiedDate":"2015-09-30T19:40:57.253","DeletedBy":null,"DeletedDate":null,"RefID":null,"HelpMStorageServerId":null,"HelpMFilePath":null,"HelpMMineType":null,"HelpMFileLength":null,"HelpMCreateDate":null,"HelpMUpdateDate":null,"DetailType":"Major","ForSE":true,"ForQA":false,"IsMandatoryCapture":"N"},{"DetailID":34827,"VersionNumber":1,"HeaderID":8493,"ScoreID":0,"SubjectID":null,"GroupName":"","DetailName":"วาง Sleeves ท่อพร้อมเหล็กเสริมถูกต้องและครบถ้วน","Seq":7,"Status":null,"Remark":null,"CreatedBy":2420,"CreatedDate":"2015-09-30T19:40:57.253","ModifiedBy":2420,"ModifiedDate":"2015-09-30T19:40:57.253","DeletedBy":null,"DeletedDate":null,"RefID":null,"HelpMStorageServerId":null,"HelpMFilePath":null,"HelpMMineType":null,"HelpMFileLength":null,"HelpMCreateDate":null,"HelpMUpdateDate":null,"DetailType":"Major","ForSE":true,"ForQA":false,"IsMandatoryCapture":"N"},{"DetailID":34828,"VersionNumber":1,"HeaderID":8493,"ScoreID":0,"SubjectID":null,"GroupName":"","DetailName":"จับปุ่มทำระดับทุกระยะไม่เกิน 1.50 m พร้อมระดับเทข้างแบบ","Seq":8,"Status":null,"Remark":null,"CreatedBy":2420,"CreatedDate":"2015-09-30T19:40:57.253","ModifiedBy":2420,"ModifiedDate":"2015-09-30T19:40:57.253","DeletedBy":null,"DeletedDate":null,"RefID":null,"HelpMStorageServerId":null,"HelpMFilePath":null,"HelpMMineType":null,"HelpMFileLength":null,"HelpMCreateDate":null,"HelpMUpdateDate":null,"DetailType":"Major","ForSE":true,"ForQA":false,"IsMandatoryCapture":"N"},{"DetailID":34829,"VersionNumber":1,"HeaderID":8494,"ScoreID":0,"SubjectID":null,"GroupName":"","DetailName":"แบบหล่อคอนกรีตติดตั้งได้มั่นคงแข็งแรง   รอยต่อแบบต้องแนบสนิทกันทุกด้าน","Seq":1,"Status":null,"Remark":null,"CreatedBy":2420,"CreatedDate":"2015-09-30T19:40:57.253","ModifiedBy":2420,"ModifiedDate":"2015-09-30T19:40:57.253","DeletedBy":null,"DeletedDate":null,"RefID":null,"HelpMStorageServerId":null,"HelpMFilePath":null,"HelpMMineType":null,"HelpMFileLength":null,"HelpMCreateDate":null,"HelpMUpdateDate":null,"DetailType":"Major","ForSE":true,"ForQA":false,"IsMandatoryCapture":"N"},{"DetailID":34830,"VersionNumber":1,"HeaderID":8494,"ScoreID":0,"SubjectID":null,"GroupName":"","DetailName":"ติดตั้งเหล็กเสริมต่างๆถูกต้องทั้งขนาด  จำนวน  ระยะห่าง  โดยผูกยึดไว้อย่างแข็งแรง","Seq":2,"Status":null,"Remark":null,"CreatedBy":2420,"CreatedDate":"2015-09-30T19:40:57.253","ModifiedBy":2420,"ModifiedDate":"2015-09-30T19:40:57.253","DeletedBy":null,"DeletedDate":null,"RefID":null,"HelpMStorageServerId":null,"HelpMFilePath":null,"HelpMMineType":null,"HelpMFileLength":null,"HelpMCreateDate":null,"HelpMUpdateDate":null,"DetailType":"Major","ForSE":true,"ForQA":false,"IsMandatoryCapture":"N"}],"LastSyncDate":"0001-01-01T00:00:00","DataRelatedChangeCode":"f54d0203-ac9c-4ce1-826e-97351d3531fe"}
